LFindb/__init__.py
LFindb/config.py
LFindb/mysql_db.py
LFindb/trade.py
LFindb-0.0.1.dist-info/LICENSE.txt
LFindb-0.0.1.dist-info/METADATA
LFindb-0.0.1.dist-info/WHEEL
LFindb-0.0.1.dist-info/top_level.txt
LFindb-0.0.1.dist-info/RECORD
